biotmed_device_sdk/__init__.py
biotmed_device_sdk/api_client.py
biotmed_device_sdk/api_response.py
biotmed_device_sdk/configuration.py
biotmed_device_sdk/exceptions.py
biotmed_device_sdk/py.typed
biotmed_device_sdk/rest.py
biotmed_device_sdk/api/__init__.py
biotmed_device_sdk/api/command_api_api.py
biotmed_device_sdk/api/device_alert_api_api.py
biotmed_device_sdk/api/device_api_api.py
biotmed_device_sdk/api/device_certificate_api_api.py
biotmed_device_sdk/api/endpoint_api_api.py
biotmed_device_sdk/api/health_check_api_api.py
biotmed_device_sdk/api/temporary_credentials_api_api.py
biotmed_device_sdk/api/temporary_token_operation_api_api.py
biotmed_device_sdk/api/usage_session_api_api.py
biotmed_device_sdk/api/usage_session_remote_control_api_api.py
biotmed_device_sdk/models/__init__.py
biotmed_device_sdk/models/basic_entity_data.py
biotmed_device_sdk/models/basic_referenced_entity_data_string_id.py
biotmed_device_sdk/models/basic_referenced_entity_data_uuidid.py
biotmed_device_sdk/models/basic_template_data.py
biotmed_device_sdk/models/command_response.py
biotmed_device_sdk/models/connection_status.py
biotmed_device_sdk/models/create_alert_by_template_name_request.py
biotmed_device_sdk/models/create_alert_request.py
biotmed_device_sdk/models/create_session_by_usage_type_request_v2.py
biotmed_device_sdk/models/create_session_request_v2.py
biotmed_device_sdk/models/credentials.py
biotmed_device_sdk/models/delete_orphan_sessions_response.py
biotmed_device_sdk/models/device_alert_response.py
biotmed_device_sdk/models/device_info.py
biotmed_device_sdk/models/device_operational_status_response.py
biotmed_device_sdk/models/device_owned_alert_response.py
biotmed_device_sdk/models/device_response.py
biotmed_device_sdk/models/device_sessions_response_v2.py
biotmed_device_sdk/models/device_status.py
biotmed_device_sdk/models/endpoint_response.py
biotmed_device_sdk/models/error_response.py
biotmed_device_sdk/models/filter_v2.py
biotmed_device_sdk-2.3.40.dist-info/METADATA
biotmed_device_sdk-2.3.40.dist-info/WHEEL
biotmed_device_sdk-2.3.40.dist-info/top_level.txt
biotmed_device_sdk-2.3.40.dist-info/RECORD
